hive/config/__init__.py
hive/config/__version__.py
hive/config/testing.py
hive_config-0.0.9.dist-info/METADATA
hive_config-0.0.9.dist-info/WHEEL
hive_config-0.0.9.dist-info/top_level.txt
hive_config-0.0.9.dist-info/RECORD
