Metadata-Version: 2.1
Name: hive-config
Version: 0.0.9
Summary: Configuration management for Hive
Author-email: Gary Benson <gary@gbenson.net>
Project-URL: Homepage, https://github.com/gbenson/hive/tree/main/libs/config
Project-URL: Source, https://github.com/gbenson/hive
Requires-Dist: hive-common >=0.0.3
